PointSystem/Economy.py
PointSystem/KeepRefs.py
PointSystem/Points.py
PointSystem/__init__.py
pointsystem-1.4.0.dist-info/METADATA
pointsystem-1.4.0.dist-info/WHEEL
pointsystem-1.4.0.dist-info/licenses/LICENSE
pointsystem-1.4.0.dist-info/RECORD
