Metadata-Version: 2.1
Name: PointSystem
Version: 1.4.0
Summary: A small project for a point system
Project-URL: Homepage, https://github.com/Totallyahuman15/point-system
Project-URL: Bug Tracker, https://github.com/Totallyahuman15/point-system/issues
Author-email: Totallyahuman15 <sandfrysyt@gmail.com>
License-File: LICENSE
Classifier: Operating System :: OS Independent
Classifier: Programming Language :: Python :: 3
